tttt/button_styling.py
tttt/demo.py
tttt/test_sample.py
tttt/tttt.py
tttt/__init__.py
tttt-0.1.3.dist-info/DESCRIPTION.rst
tttt-0.1.3.dist-info/METADATA
tttt-0.1.3.dist-info/metadata.json
tttt-0.1.3.dist-info/pbr.json
tttt-0.1.3.dist-info/RECORD
tttt-0.1.3.dist-info/top_level.txt
tttt-0.1.3.dist-info/WHEEL
