Metadata-Version: 2.0
Name: tttt
Version: 0.1.3
Summary: Python3 tkinter text plugin - easily save and load multiple font styles
Home-page: https://github.com/timeyyy/tttt
Author: timothy eichler
Author-email: tim_eichler@hotmail.com
License: BSD
Keywords: tkinter text font style bold underline italic color
Platform: UNKNOWN
Classifier: Development Status :: 3 - Alpha
Classifier: Intended Audience :: Developers
Classifier: License :: OSI Approved :: BSD License
Classifier: Programming Language :: Python :: 3
Classifier: Programming Language :: Python :: 3.2
Classifier: Programming Language :: Python :: 3.3
Classifier: Programming Language :: Python :: 3.4
Classifier: Programming Language :: Python :: 3.5
